devsim/__init__.py
devsim/devsim_py3.so
devsim/python_packages/Klaassen.py
devsim/python_packages/__init__.py
devsim/python_packages/fermi_physics.py
devsim/python_packages/model_create.py
devsim/python_packages/mos_physics.py
devsim/python_packages/pythonmesh.py
devsim/python_packages/ramp.py
devsim/python_packages/simple_dd.py
devsim/python_packages/simple_physics.py
devsim/umfpack/libumfpack_lgpl.so
devsim/umfpack/umfpack_loader.py
devsim/umfpack/umfshim.py
devsim-2.10.0.data/data/devsim_data/BUILD.md
devsim-2.10.0.data/data/devsim_data/CHANGES.md
devsim-2.10.0.data/data/devsim_data/CITATION.md
devsim-2.10.0.data/data/devsim_data/CODE_OF_CONDUCT.md
devsim-2.10.0.data/data/devsim_data/CONTRIBUTING.md
devsim-2.10.0.data/data/devsim_data/HOWTO.md
devsim-2.10.0.data/data/devsim_data/INSTALL.md
devsim-2.10.0.data/data/devsim_data/README.md
devsim-2.10.0.data/data/devsim_data/TEST.md
devsim-2.10.0.data/data/devsim_data/setup.cfg
devsim-2.10.0.data/data/devsim_data/setup.py
devsim-2.10.0.data/data/devsim_data/doc/devsim.pdf
devsim-2.10.0.data/data/devsim_data/doc/symdiff.pdf
devsim-2.10.0.data/data/devsim_data/examples/bioapp1/Ve0.jpg
devsim-2.10.0.data/data/devsim_data/examples/bioapp1/Ve0_3d.jpg
devsim-2.10.0.data/data/devsim_data/examples/bioapp1/Ve7.jpg
devsim-2.10.0.data/data/devsim_data/examples/bioapp1/Ve7_3d.jpg
devsim-2.10.0.data/data/devsim_data/examples/bioapp1/bioapp1_2d.py
devsim-2.10.0.data/data/devsim_data/examples/bioapp1/bioapp1_3d.py
devsim-2.10.0.data/data/devsim_data/examples/bioapp1/bioapp1_common.py
devsim-2.10.0.data/data/devsim_data/examples/bioapp1/disk_2d.geo
devsim-2.10.0.data/data/devsim_data/examples/bioapp1/disk_2d.msh
devsim-2.10.0.data/data/devsim_data/examples/bioapp1/disk_3d.geo
devsim-2.10.0.data/data/devsim_data/examples/bioapp1/disk_3d.msh
devsim-2.10.0.data/data/devsim_data/examples/capacitance/cap.lay
devsim-2.10.0.data/data/devsim_data/examples/capacitance/cap1d.py
devsim-2.10.0.dist-info/METADATA
devsim-2.10.0.dist-info/WHEEL
devsim-2.10.0.dist-info/top_level.txt
devsim-2.10.0.dist-info/RECORD
devsim-2.10.0.dist-info/licenses/LICENSE
devsim-2.10.0.dist-info/licenses/NOTICE
