Metadata-Version: 2.4
Name: devsim
Version: 2.10.0
Summary: DEVSIM: TCAD Device Simulator
Home-page: https://devsim.org
Author: Juan Sanchez and others
Author-email: info@devsim.com
License: Apache License, Version 2.0
Project-URL: Bug Tracker, https://github.com/devsim/devsim/issues
Project-URL: Documentation, https://devsim.net
Project-URL: Source Code, https://github.com/devsim/devsim
Project-URL: Online Forum, https://forum.devsim.org
Classifier: Development Status :: 5 - Production/Stable
Classifier: Intended Audience :: Science/Research
Classifier: License :: OSI Approved :: Apache Software License
Classifier: Programming Language :: Python :: 3
Classifier: Topic :: Scientific/Engineering :: Electronic Design Automation (EDA)
License-File: LICENSE
License-File: NOTICE
Dynamic: description
Dynamic: description-content-type
Dynamic: license-file
